{
    "asset": {
        "format": "jpg",
        "id": "0a83557eb91c2d05004907ef0968918a",
        "name": "DJI_0289_LI.jpg",
        "path": "file:C:/Users/gonza/OneDrive/Desktop/11-20/DJI_0289_LI.jpg",
        "size": {
            "width": 5472,
            "height": 3648
        },
        "state": 2,
        "type": 1
    },
    "regions": [
        {
            "id": "t_iF26Z3T",
            "type": "RECTANGLE",
            "tags": [
                "yacaré"
            ],
            "boundingBox": {
                "height": 115.41691770391948,
                "width": 131.90495895127117,
                "left": 3873.166164592161,
                "top": 985.166164592161
            },
            "points": [
                {
                    "x": 3873.166164592161,
                    "y": 985.166164592161
                },
                {
                    "x": 4005.071123543432,
                    "y": 985.166164592161
                },
                {
                    "x": 4005.071123543432,
                    "y": 1100.5830822960804
                },
                {
                    "x": 3873.166164592161,
                    "y": 1100.5830822960804
                }
            ]
        },
        {
            "id": "tWIFkz_4o",
            "type": "RECTANGLE",
            "tags": [
                "yacaré"
            ],
            "boundingBox": {
                "height": 70.07460771980932,
                "width": 119.5387314618644,
                "left": 3906.1425615730927,
                "top": 313.2745919954979
            },
            "points": [
                {
                    "x": 3906.1425615730927,
                    "y": 313.2745919954979
                },
                {
                    "x": 4025.6812930349574,
                    "y": 313.2745919954979
                },
                {
                    "x": 4025.6812930349574,
                    "y": 383.3491997153072
                },
                {
                    "x": 3906.1425615730927,
                    "y": 383.3491997153072
                }
            ]
        },
        {
            "id": "2sfR39xoa",
            "type": "RECTANGLE",
            "tags": [
                "yacaré"
            ],
            "boundingBox": {
                "height": 86.56280621027541,
                "width": 53.58640922934322,
                "left": 1350.4813873808262,
                "top": 1248.9762397378177
            },
            "points": [
                {
                    "x": 1350.4813873808262,
                    "y": 1248.9762397378177
                },
                {
                    "x": 1404.0677966101694,
                    "y": 1248.9762397378177
                },
                {
                    "x": 1404.0677966101694,
                    "y": 1335.5390459480932
                },
                {
                    "x": 1350.4813873808262,
                    "y": 1335.5390459480932
                }
            ]
        }
    ],
    "version": "2.2.0"
}