{
    "asset": {
        "format": "JPG",
        "id": "842b5cc2e83d56d4c4e043ce3f26b939",
        "name": "DJI_1260.JPG",
        "path": "file:E:/Gonzalo/Invierno%202023/Esquina/29%20a%2031%20de%20agosto%20de%202023/31%20de%20agosto%20-%20Laguna%20pore'%C5%B7/13%20-%2012/DJI_1260.JPG",
        "size": {
            "width": 4864,
            "height": 3648
        },
        "state": 2,
        "type": 1
    },
    "regions": [
        {
            "id": "_icy8rSUi",
            "type": "RECTANGLE",
            "tags": [
                "carpincho"
            ],
            "boundingBox": {
                "height": 41.220338983050844,
                "width": 57.70853747351695,
                "left": 2884.9086003707625,
                "top": 3606.779661016949
            },
            "points": [
                {
                    "x": 2884.9086003707625,
                    "y": 3606.779661016949
                },
                {
                    "x": 2942.6171378442796,
                    "y": 3606.779661016949
                },
                {
                    "x": 2942.6171378442796,
                    "y": 3647.9999999999995
                },
                {
                    "x": 2884.9086003707625,
                    "y": 3647.9999999999995
                }
            ]
        },
        {
            "id": "0jBAAjFGH",
            "type": "RECTANGLE",
            "tags": [
                "carpincho"
            ],
            "boundingBox": {
                "height": 57.70853747351695,
                "width": 61.83050847457626,
                "left": 2765.3695544226694,
                "top": 2947.2542372881353
            },
            "points": [
                {
                    "x": 2765.3695544226694,
                    "y": 2947.2542372881353
                },
                {
                    "x": 2827.2000628972455,
                    "y": 2947.2542372881353
                },
                {
                    "x": 2827.2000628972455,
                    "y": 3004.9627747616523
                },
                {
                    "x": 2765.3695544226694,
                    "y": 3004.9627747616523
                }
            ]
        },
        {
            "id": "957tAgP7E",
            "type": "RECTANGLE",
            "tags": [
                "yacaré"
            ],
            "boundingBox": {
                "height": 136.0272444385593,
                "width": 86.56296345338983,
                "left": 4673.871060646186,
                "top": 3338.8474576271183
            },
            "points": [
                {
                    "x": 4673.871060646186,
                    "y": 3338.8474576271183
                },
                {
                    "x": 4760.434024099576,
                    "y": 3338.8474576271183
                },
                {
                    "x": 4760.434024099576,
                    "y": 3474.874702065678
                },
                {
                    "x": 4673.871060646186,
                    "y": 3474.874702065678
                }
            ]
        },
        {
            "id": "6pwH-40a4",
            "type": "RECTANGLE",
            "tags": [
                "carpincho"
            ],
            "boundingBox": {
                "height": 49.46428098516949,
                "width": 49.464595471398304,
                "left": 2876.664343882415,
                "top": 2996.7188327595336
            },
            "points": [
                {
                    "x": 2876.664343882415,
                    "y": 2996.7188327595336
                },
                {
                    "x": 2926.128939353813,
                    "y": 2996.7188327595336
                },
                {
                    "x": 2926.128939353813,
                    "y": 3046.183113744703
                },
                {
                    "x": 2876.664343882415,
                    "y": 3046.183113744703
                }
            ]
        },
        {
            "id": "c1Y68Yp1M",
            "type": "RECTANGLE",
            "tags": [
                "ave"
            ],
            "boundingBox": {
                "height": 28.854268736758474,
                "width": 37.098053495762706,
                "left": 4628.529065148305,
                "top": 1347.9051161943855
            },
            "points": [
                {
                    "x": 4628.529065148305,
                    "y": 1347.9051161943855
                },
                {
                    "x": 4665.627118644067,
                    "y": 1347.9051161943855
                },
                {
                    "x": 4665.627118644067,
                    "y": 1376.759384931144
                },
                {
                    "x": 4628.529065148305,
                    "y": 1376.759384931144
                }
            ]
        },
        {
            "id": "Qp4yJ6QKh",
            "type": "RECTANGLE",
            "tags": [
                "yacaré"
            ],
            "boundingBox": {
                "height": 78.31870696504237,
                "width": 86.56264896716101,
                "left": 1994.54934123411,
                "top": 1760.108506024894
            },
            "points": [
                {
                    "x": 1994.54934123411,
                    "y": 1760.108506024894
                },
                {
                    "x": 2081.111990201271,
                    "y": 1760.108506024894
                },
                {
                    "x": 2081.111990201271,
                    "y": 1838.4272129899364
                },
                {
                    "x": 1994.54934123411,
                    "y": 1838.4272129899364
                }
            ]
        },
        {
            "id": "5wVzTA_jQ",
            "type": "RECTANGLE",
            "tags": [
                "ave"
            ],
            "boundingBox": {
                "height": 24.732219114141948,
                "width": 28.854111493644066,
                "left": 815.6475519729872,
                "top": 820.2847300384003
            },
            "points": [
                {
                    "x": 815.6475519729872,
                    "y": 820.2847300384003
                },
                {
                    "x": 844.5016634666313,
                    "y": 820.2847300384003
                },
                {
                    "x": 844.5016634666313,
                    "y": 845.0169491525423
                },
                {
                    "x": 815.6475519729872,
                    "y": 845.0169491525423
                }
            ]
        },
        {
            "id": "IY5V9VgUa",
            "type": "RECTANGLE",
            "tags": [
                "ave"
            ],
            "boundingBox": {
                "height": 28.854111493644066,
                "width": 28.85442597987288,
                "left": 2423.2406150688557,
                "top": 3573.8035785222455
            },
            "points": [
                {
                    "x": 2423.2406150688557,
                    "y": 3573.8035785222455
                },
                {
                    "x": 2452.0950410487285,
                    "y": 3573.8035785222455
                },
                {
                    "x": 2452.0950410487285,
                    "y": 3602.6576900158893
                },
                {
                    "x": 2423.2406150688557,
                    "y": 3602.6576900158893
                }
            ]
        }
    ],
    "version": "2.2.0"
}