{
    "asset": {
        "format": "JPG",
        "id": "d71c5e2af9b52424cc4834c60edc5a30",
        "name": "DJI_0533.JPG",
        "path": "file:D:/Gonzalo/Invierno%202021/Fisco%20(25%20de%20agosto%20del%202021)/Vuelos%20dron%20Fisco%20Agosto%2021%20(1)/DJI_0533.JPG",
        "size": {
            "width": 4864,
            "height": 3648
        },
        "state": 2,
        "type": 1
    },
    "regions": [
        {
            "id": "43ZSJsUSg",
            "type": "RECTANGLE",
            "tags": [
                "vehículo"
            ],
            "boundingBox": {
                "height": 894.4815446239406,
                "width": 577.0847457627118,
                "left": 2414.996673066737,
                "top": 2596.8813559322034
            },
            "points": [
                {
                    "x": 2414.996673066737,
                    "y": 2596.8813559322034
                },
                {
                    "x": 2992.081418829449,
                    "y": 2596.8813559322034
                },
                {
                    "x": 2992.081418829449,
                    "y": 3491.362900556144
                },
                {
                    "x": 2414.996673066737,
                    "y": 3491.362900556144
                }
            ]
        }
    ],
    "version": "2.2.0"
}